PyArgsMaker/__init__.py
PyArgsMake-0.1.dist-info/METADATA
PyArgsMake-0.1.dist-info/WHEEL
PyArgsMake-0.1.dist-info/top_level.txt
PyArgsMake-0.1.dist-info/RECORD
