Metadata-Version: 2.1
Name: PyArgsMake
Version: 0.1
Summary: Lib for args in python
Author: DanXvo
Author-email: daniilgrandhvo@gmail.com
Classifier: Programming Language :: Python :: 3
Classifier: License :: OSI Approved :: MIT License
Classifier: Operating System :: OS Independent
Requires-Python: >=3.6
